diagon/__init__.py
diagon-0.0.1.dist-info/METADATA
diagon-0.0.1.dist-info/WHEEL
diagon-0.0.1.dist-info/top_level.txt
diagon-0.0.1.dist-info/RECORD
