Metadata-Version: 2.4
Name: diagon
Version: 0.0.1
Summary: Diagon: data validation, scenario management, and utilities
Author-email: Tim Marquart <tmarquart@gmail.com>
License: MIT
Keywords: data,validation,utilities,scenario
Classifier: Development Status :: 1 - Planning
Classifier: Intended Audience :: Developers
Classifier: License :: OSI Approved :: Apache Software License
Classifier: Programming Language :: Python :: 3
Classifier: Topic :: Scientific/Engineering :: Information Analysis
Requires-Python: >=3.9
